[{"id":"0","erstellt":"22.05.2021","name":"EMPTY","beschreibung":"&lt;?php echo &quot;HTML&quot;; ?&gt;","anzahl":"1","preis":"20","erledigt":false,"lastChange":"22.05.2021 12:29:53"},{"id":"1","erstellt":"22.05.2021","name":"Empty","beschreibung":"Hier steht auch text","anzahl":"2","preis":20,"erledigt":true,"lastChange":"22.05.2021 12:29:55"},{"id":2,"erstellt":"22.05.2021","name":"Empty","beschreibung":"Hier ebenso","anzahl":"3","preis":"20","erledigt":false,"lastChange":"22.05.2021 12:14:05"},{"id":3,"erstellt":"22.05.2021","name":"test","beschreibung":"test","anzahl":"1","preis":"1","erledigt":true,"lastChange":"22.05.2021 13:48:59"}]